mypackage/__init__.py
mypackage/functions.py
mypackage_osar-0.0.4.dist-info/LICENSE
mypackage_osar-0.0.4.dist-info/METADATA
mypackage_osar-0.0.4.dist-info/WHEEL
mypackage_osar-0.0.4.dist-info/top_level.txt
mypackage_osar-0.0.4.dist-info/RECORD
