Metadata-Version: 2.1
Name: mypackage-osar
Version: 0.0.4
Summary: test mypackage
Home-page: UNKNOWN
Author: Buzovskyi Vitalii
Author-email: buzovskiy.v@gmail.com
License: UNKNOWN
Platform: UNKNOWN
Classifier: Programming Language :: Python :: 3
Classifier: License :: OSI Approved :: MIT License
Classifier: Operating System :: OS Independent
Requires-Python: >=3.8
License-File: LICENSE
